{
  
  "fases": [{
    "tipo": "QuizStage",
    "pregunta": "¿Pregunta de prueba 1?",
    "respuestas": [
      {
        "text": "Primera respuesta (correcta)",
        "isCorrect": true
      },
      {
        "text": "Segunda respuesta",
        "isCorrect": false
      },
      {
        "text": "Tercera respuesta",
        "isCorrect": false
      },
      {
        "text": "Cuarta respuesta",
        "isCorrect": false
      }
    ]
    },
	{
	"tipo": "QRStage",
	"qrValue": "http://EstoEsUnaURL"
    },
    {
      "tipo": "QuizStage",
      "pregunta": "¿Pregunta de prueba 2?",
      "respuestas": [
        {
          "text": "Primera respuesta (correcta)",
          "isCorrect": true
        },
        {
          "text": "Segunda respuesta",
          "isCorrect": false
        },
        {
          "text": "Tercera respuesta (correcta)",
          "isCorrect": true
        }
      ]
    }
  ]
}